nameko_objectstorage-0.1.3.dist-info/METADATA
nameko_objectstorage-0.1.3.dist-info/RECORD
nameko_objectstorage-0.1.3.dist-info/top_level.txt
nameko_objectstorage-0.1.3.dist-info/WHEEL
nameko_objectstorage-0.1.3.dist-info/metadata.json
nameko_objectstorage-0.1.3.dist-info/zip-safe
nameko_objectstorage-0.1.3.dist-info/DESCRIPTION.rst
nameko_objectstorage/object_storage.py
nameko_objectstorage/__init__.py
