Metadata-Version: 2.0
Name: nameko-objectstorage
Version: 0.1.3
Summary: A dependency for IBM Bluemix Object Storage
Home-page: http://github.com/frisellcpl/nameko-objectstorage
Author: frisellcpl
Author-email: johan@trell.se
License: Apache License, Version 2.0
Platform: UNKNOWN
Classifier: Programming Language :: Python
Classifier: Operating System :: MacOS :: MacOS X
Classifier: Operating System :: POSIX
Classifier: Programming Language :: Python :: 3
Classifier: Programming Language :: Python :: 3.3
Classifier: Programming Language :: Python :: 3.4
Classifier: Programming Language :: Python :: 3.5
Classifier: Topic :: Internet
Classifier: Topic :: Software Development :: Libraries :: Python Modules
Classifier: Intended Audience :: Developers
Requires-Dist: nameko (==2.4.3)
